xtproductjson/__init__.py
xtproductjson/xtproductjson.py
xtproductjson-0.0.1.dist-info/LICENSE
xtproductjson-0.0.1.dist-info/METADATA
xtproductjson-0.0.1.dist-info/WHEEL
xtproductjson-0.0.1.dist-info/top_level.txt
xtproductjson-0.0.1.dist-info/RECORD
