Metadata-Version: 2.1
Name: xtproductjson
Version: 0.0.1
Summary: Can be used to convert product excel sheet to list
Home-page: https://github.com/nkman/xt-product-template-lib
Author: sg
Author-email: swatigupta01998@gmail.com
License: UNKNOWN
Platform: UNKNOWN
Classifier: Programming Language :: Python :: 3
Classifier: License :: OSI Approved :: MIT License
Classifier: Operating System :: OS Independent
Requires-Python: >=3.6
